amort/__init__.py
amort/__main__.py
amort/commandline.py
amort/tests/__init__.py
amort/tests/tests.py
amort-0.22.1.dist-info/DESCRIPTION.rst
amort-0.22.1.dist-info/METADATA
amort-0.22.1.dist-info/RECORD
amort-0.22.1.dist-info/WHEEL
amort-0.22.1.dist-info/entry_points.txt
amort-0.22.1.dist-info/metadata.json
amort-0.22.1.dist-info/top_level.txt
