Metadata-Version: 2.0
Name: amort
Version: 0.22.1
Summary: A command line application that creates amortization schedules.
Home-page: UNKNOWN
Author: Mandeep
Author-email: info@mandeep.xyz
License: GPLv3+
Platform: UNKNOWN
Classifier: Development Status :: 3 - Alpha
Classifier: License :: OSI Approved :: GNU General Public License v3 or later (GPLv3+)
Classifier: Programming Language :: Python :: 2.7
Classifier: Programming Language :: Python :: 3.4
Requires-Dist: click (==6.6)
